AFAT/__init__.py
AFAT/fibrosis.py
AFAT/fibrosis_segmentation.py
AFAT/imageJ_shapiro.py
AFAT/settings.py
hundlab_AFAT-1.0.data/scripts/AutomatedFibrosisAnalysisToolkit.py
hundlab_AFAT-1.0.dist-info/LICENSE
hundlab_AFAT-1.0.dist-info/METADATA
hundlab_AFAT-1.0.dist-info/WHEEL
hundlab_AFAT-1.0.dist-info/top_level.txt
hundlab_AFAT-1.0.dist-info/RECORD
