Metadata-Version: 2.1
Name: hundlab-AFAT
Version: 1.0
Summary: Automated Fibrosis Analysis Toolkit: A tool to quantify the amount of fibrosis in Masson’s Trichrome stains
Home-page: https://github.com/hundlab/MAT
Author: Thomas Hund
Author-email: hund.1@osu.edu
License: MIT
Platform: UNKNOWN
License-File: LICENSE
Requires-Dist: matplotlib
Requires-Dist: scipy
Requires-Dist: scikit-image
Requires-Dist: sklearn
